{"meta":{"id":"20364840-8ad5-4ea0-98a4-ca87fe900d6f","day":"February_12","map":"AmbroseValley","duration":136,"total_events":22,"humans":1,"bots":0,"bot_kills":1,"bot_killed":1,"loot":3,"pvp_kills":0,"storm_deaths":0},"events":[{"uid":"ff436bfe-1b54-4098-a248-4bfbe123f3f1","human":true,"ev":"Position","ts":1770881382,"t":0,"px":77.3,"py":884.6},{"uid":"ff436bfe-1b54-4098-a248-4bfbe123f3f1","human":true,"ev":"Position","ts":1770881397,"t":15,"px":84.7,"py":882.8},{"uid":"ff436bfe-1b54-4098-a248-4bfbe123f3f1","human":true,"ev":"Position","ts":1770881402,"t":20,"px":88.3,"py":881.8},{"uid":"ff436bfe-1b54-4098-a248-4bfbe123f3f1","human":true,"ev":"Position","ts":1770881407,"t":25,"px":92.2,"py":871.3},{"uid":"ff436bfe-1b54-4098-a248-4bfbe123f3f1","human":true,"ev":"Position","ts":1770881412,"t":30,"px":111.4,"py":870.6},{"uid":"ff436bfe-1b54-4098-a248-4bfbe123f3f1","human":true,"ev":"Position","ts":1770881417,"t":35,"px":132.9,"py":868.3},{"uid":"ff436bfe-1b54-4098-a248-4bfbe123f3f1","human":true,"ev":"Position","ts":1770881422,"t":40,"px":152.3,"py":861.5},{"uid":"ff436bfe-1b54-4098-a248-4bfbe123f3f1","human":true,"ev":"Loot","ts":1770881426,"t":44,"px":162.6,"py":860.0},{"uid":"ff436bfe-1b54-4098-a248-4bfbe123f3f1","human":true,"ev":"Position","ts":1770881427,"t":45,"px":162.5,"py":859.4},{"uid":"ff436bfe-1b54-4098-a248-4bfbe123f3f1","human":true,"ev":"Position","ts":1770881432,"t":50,"px":170.5,"py":845.7},{"uid":"ff436bfe-1b54-4098-a248-4bfbe123f3f1","human":true,"ev":"Position","ts":1770881437,"t":55,"px":189.3,"py":832.9},{"uid":"ff436bfe-1b54-4098-a248-4bfbe123f3f1","human":true,"ev":"Position","ts":1770881442,"t":60,"px":207.8,"py":810.5},{"uid":"ff436bfe-1b54-4098-a248-4bfbe123f3f1","human":true,"ev":"BotKill","ts":1770881452,"t":70,"px":207.3,"py":812.7},{"uid":"ff436bfe-1b54-4098-a248-4bfbe123f3f1","human":true,"ev":"Loot","ts":1770881469,"t":87,"px":207.3,"py":816.7},{"uid":"ff436bfe-1b54-4098-a248-4bfbe123f3f1","human":true,"ev":"Loot","ts":1770881470,"t":88,"px":207.3,"py":816.7},{"uid":"ff436bfe-1b54-4098-a248-4bfbe123f3f1","human":true,"ev":"Position","ts":1770881472,"t":90,"px":207.3,"py":816.7},{"uid":"ff436bfe-1b54-4098-a248-4bfbe123f3f1","human":true,"ev":"Position","ts":1770881482,"t":100,"px":197.1,"py":831.3},{"uid":"ff436bfe-1b54-4098-a248-4bfbe123f3f1","human":true,"ev":"Position","ts":1770881487,"t":105,"px":204.1,"py":835.1},{"uid":"ff436bfe-1b54-4098-a248-4bfbe123f3f1","human":true,"ev":"Position","ts":1770881492,"t":110,"px":217.3,"py":832.8},{"uid":"ff436bfe-1b54-4098-a248-4bfbe123f3f1","human":true,"ev":"Position","ts":1770881498,"t":116,"px":215.7,"py":825.7},{"uid":"ff436bfe-1b54-4098-a248-4bfbe123f3f1","human":true,"ev":"BotKilled","ts":1770881516,"t":134,"px":218.0,"py":824.0},{"uid":"ff436bfe-1b54-4098-a248-4bfbe123f3f1","human":true,"ev":"Position","ts":1770881518,"t":136,"px":218.0,"py":824.0}]}