{"meta":{"id":"99fbbc26-7d87-4ca2-9f3b-ce960169f035","day":"February_13","map":"Lockdown","duration":127,"total_events":6,"humans":1,"agents":0,"bots":0,"bot_kills":0,"bot_killed":1,"loot":0,"pvp_kills":0,"storm_deaths":0,"outcome":"died"},"events":[{"uid":"0e070271-33e4-4cb8-9743-81fa26cab07f","type":"human","ev":"Position","t":0,"px":271.5,"py":321.2},{"uid":"0e070271-33e4-4cb8-9743-81fa26cab07f","type":"human","ev":"Position","t":25,"px":276.4,"py":325.6},{"uid":"0e070271-33e4-4cb8-9743-81fa26cab07f","type":"human","ev":"Position","t":31,"px":288.9,"py":332.0},{"uid":"0e070271-33e4-4cb8-9743-81fa26cab07f","type":"human","ev":"Position","t":36,"px":282.0,"py":316.1},{"uid":"0e070271-33e4-4cb8-9743-81fa26cab07f","type":"human","ev":"Position","t":46,"px":284.1,"py":319.3},{"uid":"0e070271-33e4-4cb8-9743-81fa26cab07f","type":"human","ev":"BotKilled","t":127,"px":284.1,"py":319.5}]}