{"meta":{"id":"cc5e1aa2-84ea-4f32-8edd-3dd180278110","day":"February_11","map":"AmbroseValley","duration":254,"total_events":48,"humans":1,"bots":0,"bot_kills":2,"bot_killed":1,"loot":10,"pvp_kills":0,"storm_deaths":0},"events":[{"uid":"f39d1c2e-6948-4ee4-b9de-9b7d7aba0060","human":true,"ev":"Position","ts":1770769280,"t":0,"px":62.0,"py":489.3},{"uid":"f39d1c2e-6948-4ee4-b9de-9b7d7aba0060","human":true,"ev":"Position","ts":1770769300,"t":20,"px":79.3,"py":467.5},{"uid":"f39d1c2e-6948-4ee4-b9de-9b7d7aba0060","human":true,"ev":"Position","ts":1770769305,"t":25,"px":91.3,"py":449.0},{"uid":"f39d1c2e-6948-4ee4-b9de-9b7d7aba0060","human":true,"ev":"Position","ts":1770769310,"t":30,"px":97.1,"py":422.3},{"uid":"f39d1c2e-6948-4ee4-b9de-9b7d7aba0060","human":true,"ev":"Position","ts":1770769315,"t":35,"px":99.4,"py":416.8},{"uid":"f39d1c2e-6948-4ee4-b9de-9b7d7aba0060","human":true,"ev":"Position","ts":1770769320,"t":40,"px":102.0,"py":406.8},{"uid":"f39d1c2e-6948-4ee4-b9de-9b7d7aba0060","human":true,"ev":"Loot","ts":1770769322,"t":42,"px":106.3,"py":404.4},{"uid":"f39d1c2e-6948-4ee4-b9de-9b7d7aba0060","human":true,"ev":"Position","ts":1770769326,"t":46,"px":104.7,"py":409.0},{"uid":"f39d1c2e-6948-4ee4-b9de-9b7d7aba0060","human":true,"ev":"Loot","ts":1770769327,"t":47,"px":104.7,"py":409.0},{"uid":"f39d1c2e-6948-4ee4-b9de-9b7d7aba0060","human":true,"ev":"Position","ts":1770769331,"t":51,"px":98.5,"py":408.9},{"uid":"f39d1c2e-6948-4ee4-b9de-9b7d7aba0060","human":true,"ev":"Loot","ts":1770769334,"t":54,"px":98.4,"py":408.2},{"uid":"f39d1c2e-6948-4ee4-b9de-9b7d7aba0060","human":true,"ev":"Position","ts":1770769336,"t":56,"px":91.3,"py":408.0},{"uid":"f39d1c2e-6948-4ee4-b9de-9b7d7aba0060","human":true,"ev":"Loot","ts":1770769337,"t":57,"px":90.4,"py":407.9},{"uid":"f39d1c2e-6948-4ee4-b9de-9b7d7aba0060","human":true,"ev":"Position","ts":1770769341,"t":61,"px":97.9,"py":408.5},{"uid":"f39d1c2e-6948-4ee4-b9de-9b7d7aba0060","human":true,"ev":"Position","ts":1770769346,"t":66,"px":104.4,"py":400.0},{"uid":"f39d1c2e-6948-4ee4-b9de-9b7d7aba0060","human":true,"ev":"Position","ts":1770769351,"t":71,"px":94.6,"py":394.7},{"uid":"f39d1c2e-6948-4ee4-b9de-9b7d7aba0060","human":true,"ev":"Loot","ts":1770769354,"t":74,"px":94.7,"py":395.0},{"uid":"f39d1c2e-6948-4ee4-b9de-9b7d7aba0060","human":true,"ev":"Position","ts":1770769356,"t":76,"px":95.3,"py":399.1},{"uid":"f39d1c2e-6948-4ee4-b9de-9b7d7aba0060","human":true,"ev":"Loot","ts":1770769358,"t":78,"px":95.2,"py":399.4},{"uid":"f39d1c2e-6948-4ee4-b9de-9b7d7aba0060","human":true,"ev":"Position","ts":1770769361,"t":81,"px":99.6,"py":390.3},{"uid":"f39d1c2e-6948-4ee4-b9de-9b7d7aba0060","human":true,"ev":"Position","ts":1770769366,"t":86,"px":120.6,"py":403.8},{"uid":"f39d1c2e-6948-4ee4-b9de-9b7d7aba0060","human":true,"ev":"Position","ts":1770769371,"t":91,"px":148.3,"py":396.5},{"uid":"f39d1c2e-6948-4ee4-b9de-9b7d7aba0060","human":true,"ev":"Loot","ts":1770769371,"t":91,"px":148.0,"py":396.6},{"uid":"f39d1c2e-6948-4ee4-b9de-9b7d7aba0060","human":true,"ev":"Position","ts":1770769376,"t":96,"px":170.2,"py":406.8},{"uid":"f39d1c2e-6948-4ee4-b9de-9b7d7aba0060","human":true,"ev":"Position","ts":1770769381,"t":101,"px":198.3,"py":411.4},{"uid":"f39d1c2e-6948-4ee4-b9de-9b7d7aba0060","human":true,"ev":"Position","ts":1770769386,"t":106,"px":216.8,"py":406.5},{"uid":"f39d1c2e-6948-4ee4-b9de-9b7d7aba0060","human":true,"ev":"Position","ts":1770769391,"t":111,"px":239.9,"py":410.7},{"uid":"f39d1c2e-6948-4ee4-b9de-9b7d7aba0060","human":true,"ev":"Position","ts":1770769396,"t":116,"px":266.0,"py":417.7},{"uid":"f39d1c2e-6948-4ee4-b9de-9b7d7aba0060","human":true,"ev":"Position","ts":1770769401,"t":121,"px":279.5,"py":430.2},{"uid":"f39d1c2e-6948-4ee4-b9de-9b7d7aba0060","human":true,"ev":"Loot","ts":1770769402,"t":122,"px":280.1,"py":430.5},{"uid":"f39d1c2e-6948-4ee4-b9de-9b7d7aba0060","human":true,"ev":"Position","ts":1770769406,"t":126,"px":278.2,"py":437.0},{"uid":"f39d1c2e-6948-4ee4-b9de-9b7d7aba0060","human":true,"ev":"Position","ts":1770769411,"t":131,"px":278.9,"py":436.3},{"uid":"f39d1c2e-6948-4ee4-b9de-9b7d7aba0060","human":true,"ev":"Position","ts":1770769416,"t":136,"px":277.7,"py":435.2},{"uid":"f39d1c2e-6948-4ee4-b9de-9b7d7aba0060","human":true,"ev":"Position","ts":1770769421,"t":141,"px":280.0,"py":436.3},{"uid":"f39d1c2e-6948-4ee4-b9de-9b7d7aba0060","human":true,"ev":"Position","ts":1770769436,"t":156,"px":287.8,"py":458.7},{"uid":"f39d1c2e-6948-4ee4-b9de-9b7d7aba0060","human":true,"ev":"BotKill","ts":1770769443,"t":163,"px":287.3,"py":459.8},{"uid":"f39d1c2e-6948-4ee4-b9de-9b7d7aba0060","human":true,"ev":"Position","ts":1770769446,"t":166,"px":295.6,"py":458.3},{"uid":"f39d1c2e-6948-4ee4-b9de-9b7d7aba0060","human":true,"ev":"Position","ts":1770769451,"t":171,"px":304.8,"py":458.7},{"uid":"f39d1c2e-6948-4ee4-b9de-9b7d7aba0060","human":true,"ev":"Loot","ts":1770769452,"t":172,"px":304.8,"py":458.7},{"uid":"f39d1c2e-6948-4ee4-b9de-9b7d7aba0060","human":true,"ev":"Loot","ts":1770769453,"t":173,"px":304.8,"py":458.7},{"uid":"f39d1c2e-6948-4ee4-b9de-9b7d7aba0060","human":true,"ev":"BotKill","ts":1770769462,"t":182,"px":304.8,"py":458.7},{"uid":"f39d1c2e-6948-4ee4-b9de-9b7d7aba0060","human":true,"ev":"Position","ts":1770769466,"t":186,"px":305.4,"py":456.3},{"uid":"f39d1c2e-6948-4ee4-b9de-9b7d7aba0060","human":true,"ev":"Position","ts":1770769476,"t":196,"px":305.2,"py":458.6},{"uid":"f39d1c2e-6948-4ee4-b9de-9b7d7aba0060","human":true,"ev":"Position","ts":1770769486,"t":206,"px":333.2,"py":451.9},{"uid":"f39d1c2e-6948-4ee4-b9de-9b7d7aba0060","human":true,"ev":"Position","ts":1770769491,"t":211,"px":345.6,"py":442.1},{"uid":"f39d1c2e-6948-4ee4-b9de-9b7d7aba0060","human":true,"ev":"Position","ts":1770769496,"t":216,"px":348.5,"py":435.4},{"uid":"f39d1c2e-6948-4ee4-b9de-9b7d7aba0060","human":true,"ev":"Position","ts":1770769502,"t":222,"px":343.9,"py":442.7},{"uid":"f39d1c2e-6948-4ee4-b9de-9b7d7aba0060","human":true,"ev":"BotKilled","ts":1770769534,"t":254,"px":343.1,"py":442.5}]}